ecovent/__init__.py
pyEcovent-0.8.4.dist-info/DESCRIPTION.rst
pyEcovent-0.8.4.dist-info/METADATA
pyEcovent-0.8.4.dist-info/RECORD
pyEcovent-0.8.4.dist-info/WHEEL
pyEcovent-0.8.4.dist-info/metadata.json
pyEcovent-0.8.4.dist-info/top_level.txt
