Metadata-Version: 2.0
Name: pyEcovent
Version: 0.8.4
Summary: Python3 library for single-room energy recovery ventilators from Vents / Blauberg / Flexit
Home-page: https://github.com/aglehmann/pyEcovent
Author: Aleksander Lehmann
Author-email: aleksander@flovik.no
License: MIT
Platform: UNKNOWN
Classifier: Intended Audience :: Developers
Classifier: Operating System :: OS Independent
Classifier: Programming Language :: Python
Classifier: Programming Language :: Python :: 3
Classifier: Topic :: Home Automation
Classifier: Topic :: Software Development :: Libraries :: Python Modules
Requires-Python: >=3.6.7
